odoo/addons/delivery_carrier_manual_weight/README.rst
odoo/addons/delivery_carrier_manual_weight/__init__.py
odoo/addons/delivery_carrier_manual_weight/__manifest__.py
odoo/addons/delivery_carrier_manual_weight/i18n/delivery_carrier_manual_weight.pot
odoo/addons/delivery_carrier_manual_weight/i18n/it.po
odoo/addons/delivery_carrier_manual_weight/models/__init__.py
odoo/addons/delivery_carrier_manual_weight/models/delivery_carrier.py
odoo/addons/delivery_carrier_manual_weight/models/stock_picking.py
odoo/addons/delivery_carrier_manual_weight/readme/CONTRIBUTORS.md
odoo/addons/delivery_carrier_manual_weight/readme/DESCRIPTION.md
odoo/addons/delivery_carrier_manual_weight/readme/USAGE.md
odoo/addons/delivery_carrier_manual_weight/static/description/icon.png
odoo/addons/delivery_carrier_manual_weight/static/description/index.html
odoo/addons/delivery_carrier_manual_weight/tests/__init__.py
odoo/addons/delivery_carrier_manual_weight/tests/test_delivery_carrier_manual_weight.py
odoo/addons/delivery_carrier_manual_weight/views/delivery_view.xml
odoo_addon_delivery_carrier_manual_weight-18.0.1.0.0.2.dist-info/METADATA
odoo_addon_delivery_carrier_manual_weight-18.0.1.0.0.2.dist-info/WHEEL
odoo_addon_delivery_carrier_manual_weight-18.0.1.0.0.2.dist-info/top_level.txt
odoo_addon_delivery_carrier_manual_weight-18.0.1.0.0.2.dist-info/RECORD
